MANIFEST.in
README.txt
setup.py
MD_ELM.egg-info/PKG-INFO
MD_ELM.egg-info/SOURCES.txt
MD_ELM.egg-info/dependency_links.txt
MD_ELM.egg-info/top_level.txt
mdelm/__init__.py
mdelm/mdelm.py
mdelm/mdelm_method.py
opelm/__init__.py
opelm/elm.py
opelm/mrsr.py
opelm/slfn.py