Metadata-Version: 1.0
Name: MD-ELM
Version: 0.61
Summary: Mislabeled samples detection with OP-ELM
Home-page: UNKNOWN
Author: Anton Akusok
Author-email: akusok.a@gmail.com
License: MIT
Platform: UNKNOWN
